settings_model/__init__.py
settings_model/admin.py
settings_model/apps.py
settings_model/base.py
settings_model/model_settings.py
settings_model/models.py
settings_model/settings.py
settings_model/tests.py
settings_model/urls.py
settings_model/wsgi.py
settings_model/migrations/0001_initial.py
settings_model/migrations/__init__.py
django_settings_model-0.6.0.dist-info/LICENSE
django_settings_model-0.6.0.dist-info/METADATA
django_settings_model-0.6.0.dist-info/WHEEL
django_settings_model-0.6.0.dist-info/top_level.txt
django_settings_model-0.6.0.dist-info/RECORD
