Metadata-Version: 2.1
Name: django-settings-model
Version: 0.6.0
Summary: A re-useable Django app for building models that modify Django settings.
Home-page: https://github.com/gregschmit/django-settings-model
Author: Gregory N. Schmit
Author-email: me@gregschmit.com
License: MIT
Platform: UNKNOWN
Classifier: Environment :: Web Environment
Classifier: Framework :: Django
Classifier: Intended Audience :: Developers
Classifier: License :: OSI Approved :: MIT License
Classifier: Programming Language :: Python :: 3
Requires-Dist: Django (>=2)
Requires-Dist: pytz
